MANIFEST.in
setup.py
src/fsqio/__init__.py
src/fsqio.pants.buildgen.core.egg-info/PKG-INFO
src/fsqio.pants.buildgen.core.egg-info/SOURCES.txt
src/fsqio.pants.buildgen.core.egg-info/dependency_links.txt
src/fsqio.pants.buildgen.core.egg-info/namespace_packages.txt
src/fsqio.pants.buildgen.core.egg-info/requires.txt
src/fsqio.pants.buildgen.core.egg-info/top_level.txt
src/fsqio.pants.buildgen.core.egg-info/zip-safe
src/fsqio/pants/__init__.py
src/fsqio/pants/buildgen/__init__.py
src/fsqio/pants/buildgen/core/__init__.py
src/fsqio/pants/buildgen/core/build_file_manipulator.py
src/fsqio/pants/buildgen/core/buildgen.py
src/fsqio/pants/buildgen/core/buildgen_aggregate_targets.py
src/fsqio/pants/buildgen/core/buildgen_base.py
src/fsqio/pants/buildgen/core/buildgen_target_bag.py
src/fsqio/pants/buildgen/core/buildgen_task.py
src/fsqio/pants/buildgen/core/inject_target_bags.py
src/fsqio/pants/buildgen/core/map_derived_targets.py
src/fsqio/pants/buildgen/core/map_sources_to_addresses.py
src/fsqio/pants/buildgen/core/register.py
src/fsqio/pants/buildgen/core/source_analysis_task.py
src/fsqio/pants/buildgen/core/symbol_tree.py
src/fsqio/pants/buildgen/core/third_party_map_util.py
src/fsqio/pants/buildgen/core/subsystems/__init__.py
src/fsqio/pants/buildgen/core/subsystems/buildgen_subsystem.py