Metadata-Version: 1.1
Name: fsqio.pants.buildgen.core
Version: 1.3.0
Summary: Core libraries supporting Pants buildgen.
Home-page: https://github.com/foursquare/fsqio
Author: UNKNOWN
Author-email: UNKNOWN
License: Apache License, Version 2.0
Platform: UNKNOWN
Classifier: Intended Audience :: Developers
Classifier: License :: OSI Approved :: Apache Software License
Classifier: Operating System :: MacOS :: MacOS X
Classifier: Operating System :: POSIX :: Linux
Classifier: Programming Language :: Python
Classifier: Topic :: Software Development :: Build Tools
Classifier: Topic :: Software Development :: Testing
